[
  {
    "userName": "John Doe",
    "rating": 4.5,
    "comment": "Great service! Will definitely come back.",
    "date": "2024-03-15",
    "photoURL": "https://i.ibb.co/C2YjzHH/avatar-2.jpg"
  },
  {
    "userName": "Jane Smith",
    "rating": 5,
    "comment": "Excellent experience. Highly recommended!",
    "date": "2024-03-20",
    "photoURL": "https://i.ibb.co/ZWy9J38/avatar-1.jpg"
  },
  {
    "userName": "Alice Johnson",
    "rating": 3.8,
    "comment": "Decent service, but could be improved.",
    "date": "2024-03-25",
    "photoURL": "https://i.ibb.co/C2YjzHH/avatar-2.jpg"
  },
  {
    "userName": "Bob Brown",
    "rating": 4,
    "comment": "Good overall experience.",
    "date": "2024-03-28",
    "photoURL": "https://i.ibb.co/ZWy9J38/avatar-1.jpg"
  }
]
